aura_sr.py
aura_sr-0.0.4.dist-info/LICENSE.md
aura_sr-0.0.4.dist-info/METADATA
aura_sr-0.0.4.dist-info/WHEEL
aura_sr-0.0.4.dist-info/top_level.txt
aura_sr-0.0.4.dist-info/RECORD
