Metadata-Version: 2.1
Name: aura-sr
Version: 0.0.4
Summary: GAN-based Super-Resolution for AI generated images, based on the GigaGAN architecture.
License-File: LICENSE.md
Requires-Dist: torch >=2.0
Requires-Dist: torchvision
Requires-Dist: numpy
Requires-Dist: einops
Requires-Dist: huggingface-hub
Requires-Dist: safetensors
